optimx/__init__.py
optimx/api.py
optimx/utils.py
optimx/ant/__init__.py
optimx/ant/solver.py
optimx/bases/__init__.py
optimx/bases/solver.py
optimx/knapsack/__init__.py
optimx/knapsack/base.py
optimx/knapsack/brute.py
optimx/knapsack/dynamic.py
optimx/knapsack/factory.py
optimx/knapsack/greedy.py
optimx/knapsack/solver.py
optimx/shortest_path/__init__.py
optimx/shortest_path/base.py
optimx/shortest_path/dijkstra.py
optimx/shortest_path/factory.py
optimx/tsp/__init__.py
optimx/tsp/base.py
optimx/tsp/branch.py
optimx/tsp/brute.py
optimx/tsp/dynamic.py
optimx/tsp/factory.py
optimx/tsp/nearest.py
optimx/tsp/solver.py
optimx/tsp/utility.py
optimx/tsp/visual.py
optimx-0.0.6.dist-info/METADATA
optimx-0.0.6.dist-info/WHEEL
optimx-0.0.6.dist-info/top_level.txt
optimx-0.0.6.dist-info/RECORD
